{
    "P250 | Sand Dune": "Common", "MP9 | Storm": "Common", "Nova | Walnut": "Common",
    "Dual Berettas | Anodized Navy": "Uncommon", "Glock-18 | Blue Fissure": "Uncommon",
    "M4A1-S | Blue Phosphor": "Rare", "AWP | Duality": "Rare", "AK-47 | Asiimov": "Mythical",
    "AWP | Neo-Noir": "Mythical", "AWP | Fade": "Legendary", "Karambit | Doppler": "Legendary",
    "AWP | Gungnir": "Immortal", "Karambit | Emerald": "Immortal", "AK-47 | Emerald Pinstripe": "Uncommon",
    "Desert Eagle | Conspiracy": "Rare", "USP-S | Guardian": "Mythical", "M4A4 | The Emperor": "Legendary",
    "AWP | Hyper Beast": "Mythical", "Karambit | Slaughter": "Legendary",
    "AK-47 | Aquamarine Revenge": "Legendary",
    "M4A4 | Royal Paladin": "Rare", "AWP | Redline": "Uncommon", "P2000 | Handgun": "Uncommon",
    "M4A4 | Buzz Kill": "Rare", "AK-47 | Head Shot": "Mythical", "AWP | Containment Breach": "Legendary",
    "Karambit | Lore": "Legendary", "Desert Eagle | Golden Koi": "Immortal", "AK-47 | Fire Serpent": "Immortal",
    "P250 | Asiimov": "Uncommon", "AWP | Pink DDPAT": "Common", "Glock-18 | Fade": "Mythical",
    "M4A1-S | Golden Coil": "Rare", "AWP | Dragon Lore": "Immortal", "M9 Bayonet | Gamma Doppler": "Legendary",
    "AWP | Chromatic": "Immortal", "AK-47 | Nightwish": "Legendary", "M4A4 | In Living Color": "Rare",
    "USP-S | Ticket to Hell": "Mythical", "Desert Eagle | Light Rail": "Uncommon", "Nova | Clear Cut": "Common",
    "AWP | Silk Tiger": "Mythical", "AK-47 | Neon Revolution": "Legendary", "M4A1-S | Printstream": "Immortal",
    "Glock-18 | Synth Leaf": "Rare", "Desert Eagle | Mecha Industries": "Uncommon", "P250 | Cassette": "Common",
    "AWP | Wildfire": "Mythical", "AK-47 | The Empress": "Legendary", "M4A4 | Asiimov": "Immortal",
    "USP-S | Overgrowth": "Rare", "Dual Berettas | Panthera onca": "Uncommon", "MP9 | Hot Rod": "Common",
    "AWP | Man-o'-war": "Rare", "AK-47 | Vulcan": "Mythical", "M4A1-S | Decimator": "Legendary",
    "Glock-18 | Water Elemental": "Mythical", "Desert Eagle | Code Red": "Legendary",
    "P250 | See Ya Later": "Rare",
    "M4A1 | Urban Hazard": "Common", "MP7 | Forest DDPAT": "Common", "G3SG1 | Arctic Camo": "Common",
    "SCAR-20 | Contractor": "Common", "P90 | Sand Spray": "Common", "MAC-10 | Candy Apple": "Uncommon",
    "UMP-45 | Blaze": "Uncommon", "Five-SeveN | Hot Shot": "Uncommon", "XM1014 | Grassland": "Uncommon",
    "AUG | Storm": "Uncommon", "FAMAS | Cyanospatter": "Rare", "Galil AR | Cerberus": "Rare",
    "SG 553 | Damascus Steel": "Rare", "Negev | Army Sheen": "Rare", "Tec-9 | Isaac": "Rare",
    "M4A4 | Modern Hunter": "Mythical", "AK-47 | Red Laminate": "Mythical", "AWP | Pit Viper": "Mythical",
    "Desert Eagle | Hypnotic": "Mythical", "Glock-18 | Dragon Tattoo": "Mythical", "USP-S | Orion": "Legendary",
    "M4A1-S | Knight": "Legendary", "AK-47 | Jaguar": "Legendary", "AWP | Medusa": "Immortal",
    "M4A4 | Howl": "Immortal", "AK-47 | Wild Lotus": "Immortal", "MP5-SD | Agent": "Rare",
    "PP-Bizon | Judgement of Anubis": "Mythical", "Sawed-Off | The Kraken": "Legendary",
    "M249 | Downtown": "Common", "R8 Revolver | Crimson Web": "Mythical", "CZ75-Auto | Victoria": "Legendary",
    "AK-47 | Fuel Injector": "Legendary", "M4A1-S | Icarus Fell": "Legendary", "AWP | Oni Taiji": "Legendary",
    "SSG 08 | Dragonfire": "Legendary", "Glock-18 | Wasteland Rebel": "Mythical",
    "USP-S | Kill Confirmed": "Legendary",
    "P250 | Undertow": "Rare", "Desert Eagle | Blaze": "Legendary", "M4A4 | Poseidon": "Immortal",
    "AK-47 | Hydroponic": "Immortal", "AWP | The Prince": "Immortal",
    "Karambit | Case Hardened (Blue Gem)": "Immortal",
    "FN SCAR | Bloodsport": "Mythical", "KRISS Vector | Super V": "Rare",
    "Honey Badger | Silencer": "Legendary",
    "ACR | Bushmaster": "Mythical", "G11 | Kraut Space Magic": "Legendary", "M16A4 | Burst Fire": "Uncommon",
    "AK-12 | Modernized Kalash": "Rare", "AN-94 | Hyperburst": "Mythical", "AS VAL | Subsonic": "Legendary",
    "SR-25 | Designated Marksman": "Legendary", "Barrett M82 | Anti-Materiel": "Immortal",
    "CheyTac M200 | Intervention": "Immortal", "L96A1 | Arctic Warfare": "Legendary",
    "Dragunov SVD | Marksman": "Mythical",
    "Mosin-Nagant | Bolt Action": "Uncommon", "Kar98k | Mauser": "Rare", "M1 Garand | Ping": "Rare",
    "Thompson | Chicago Typewriter": "Uncommon", "MP40 | Schmeisser": "Uncommon",
    "StG 44 | Sturmgewehr": "Rare",
    "MG42 | Buzzsaw": "Mythical", "FG42 | Paratrooper": "Legendary", "Bren LMG | Top-Mounted": "Rare",
    "Lee-Enfield | SMLE": "Uncommon", "Springfield M1903 | Sniper": "Rare", "BAR | Automatic Rifle": "Rare",
    "Colt M1911 | Old Reliable": "Common", "Luger P08 | Toggle Lock": "Uncommon",
    "Walther P38 | German Classic": "Uncommon",
    "Mauser C96 | Broomhandle": "Rare", "Webley Revolver | Top-Break": "Uncommon",
    "FN FAL | Right Arm of the Free World": "Legendary",
    "Heckler & Koch G3 | Battle Rifle": "Mythical", "Steyr AUG | Bullpup": "Rare",
    "FN F2000 | Tactical Tuna": "Mythical",
    "IMI Tavor TAR-21 | Israeli Bullpup": "Mythical", "SA80 | L85A2": "Rare",
    "FAMAS F1 | French Export": "Uncommon",
    "AK-74U | Krinkov": "Rare", "AKS-74U | Spetsnaz": "Mythical", "RPK | Light Machine Gun": "Rare",
    "PKM | General-Purpose": "Mythical", "SKS | Semi-Automatic": "Uncommon",
    "Makarov PM | Soviet Service": "Common",
    "Tokarev TT-33 | Sidearm": "Common", "Stechkin APS | Machine Pistol": "Rare",
    "Saiga-12 | Semi-Auto Shotgun": "Mythical",
    "Remington 870 | Pump-Action": "Uncommon", "Mossberg 590 | Shockwave": "Rare",
    "Benelli M4 | Super 90": "Legendary",
    "SPAS-12 | Combat Shotgun": "Mythical", "Winchester M1897 | Trench Gun": "Rare",
    "Uzi | Submachine Gun": "Uncommon",
    "Ingram MAC-10 | Machine Pistol": "Uncommon", "FN P90 | Rush B": "Rare",
    "Heckler & Koch MP7 | PDW": "Mythical",
    "Glock 19 | Compact": "Common", "SIG Sauer P226 | Navy": "Rare", "Beretta 92FS | Inox": "Uncommon",
    "Heckler & Koch USP | Tactical": "Rare", "FN Five-seveN | Armor Piercing": "Mythical",
    "Colt Python | .357 Magnum": "Legendary",
    "Smith & Wesson Model 29 | .44 Magnum": "Legendary", "IMI Desert Eagle | Point Five Oh": "Legendary",
    "Glock 18 | Full Auto": "Mythical", "Heckler & Koch G36 | German Engineering": "Mythical",
    "SIG SG 552 | Commando": "Rare", "IMI Galil | ARM": "Uncommon", "CETME Model L | Spanish Rifle": "Uncommon",
    "AR-15 | Black Rifle": "Common", "M14 | Battle Rifle": "Rare", "M21 | Sniper Weapon System": "Mythical",
    "M24 | Sniper Weapon System": "Legendary", "M40A5 | Scout Sniper": "Legendary",
    "Remington 700 | Hunting Rifle": "Uncommon",
    "Winchester Model 70 | Classic Hunter": "Rare", "Ruger 10/22 | Plinker": "Common",
    "Henry Repeating Rifle | Lever-Action": "Uncommon",
    "Colt Single Action Army | Peacemaker": "Rare", "Winchester 1887 | Lever-Action Shotgun": "Mythical",
    "Flintlock Pistol | Muzzleloader": "Common", "Blunderbuss | Scattergun": "Uncommon",
    "Musket | Brown Bess": "Rare",
    "Arquebus | Early Firearm": "Common", "Crossbow | Silent Killer": "Uncommon", "Longbow | Yew Wood": "Rare",
    "Katana | Folded Steel": "Legendary", "Nodachi | Great Sword": "Mythical", "Wakizashi | Sidearm": "Rare",
    "Tanto | Dagger": "Uncommon", "Naginata | Polearm": "Mythical", "Yari | Spear": "Uncommon",
    "Kunai | Throwing Knife": "Common", "Shuriken | Ninja Star": "Common", "Gladius | Roman Sword": "Uncommon",
    "Spatha | Cavalry Sword": "Rare", "Scutum | Tower Shield": "Mythical", "Pilum | Javelin": "Uncommon",
    "Viking Axe | Bearded Axe": "Rare", "Ulfberht | Viking Sword": "Legendary",
    "Seax | Viking Dagger": "Uncommon",
    "Round Shield | Center Grip": "Rare", "Longsword | Hand-and-a-Half": "Mythical",
    "Zweihander | Greatsword": "Legendary",
    "Estoc | Armor Piercer": "Rare", "Rapier | Fencing Sword": "Mythical",
    "Claymore | Scottish Greatsword": "Legendary",
    "Scimitar | Curved Sword": "Rare", "Khopesh | Sickle-Sword": "Mythical", "Falchion | Cleaver": "Uncommon",
    "Cutlass | Pirate's Blade": "Rare", "Mace | Skullcracker": "Uncommon", "Warhammer | Warhammer": "Mythical",
    "Flail | Chain Weapon": "Legendary", "Halberd | Poleaxe": "Mythical", "Glaive | Sword on a Pole": "Rare",
    "Trident | Three-Pronged Spear": "Legendary", "Bowie Knife | Large Sheath Knife": "Rare",
    "Kukri | Gurkha's Blade": "Mythical", "Trench Knife | Knuckle Duster": "Uncommon",
    "Ballistic Knife | Launching Blade": "Legendary", "Tomahawk | Throwing Axe": "Rare",
    "Throwing Knives | Set of Three": "Uncommon", "Spear | Simple Polearm": "Common",
    "Javelin | Light Spear": "Common", "Sling | Stone Hurler": "Common",
    "Bolas | Entangling Weapon": "Uncommon",
    "Whip | Leather Lash": "Rare", "Nunchaku | Chain-sticks": "Mythical", "Sai | Three-Pronged Dagger": "Rare",
    "Tonfa | Side-Handle Baton": "Uncommon", "Bo Staff | Long Staff": "Uncommon",
    "Railgun | Mass Driver": "Immortal", "Plasma Rifle | Directed Energy": "Legendary",
    "Laser Pistol | Sidearm Energy": "Mythical", "Gauss Rifle | Coilgun": "Immortal",
    "Particle Beam | Accelerator": "Immortal", "Sonic Emitter | Sound Weapon": "Legendary",
    "Cryo Cannon | Freeze Ray": "Mythical", "Flamethrower | Incendiary": "Mythical",
    "Grenade Launcher | M79": "Legendary", "Rocket Launcher | RPG-7": "Legendary",
    "Minigun | M134": "Immortal", "Chainsaw | Lancer": "Immortal",
    "Gravity Gun | Zero Point Energy": "Immortal",
    "Portal Gun | Aperture Science": "Immortal", "Lightsaber | Elegant Weapon": "Immortal",
    "Blaster | E-11": "Mythical", "Staff of Fire | Inferno": "Legendary",
    "Staff of Ice | Blizzard": "Legendary",
    "Staff of Lightning | Tempest": "Legendary", "Wand of Magic Missiles | Evocation": "Mythical",
    "Rod of Power | Archmage's Focus": "Immortal", "Scepter of Kings | Royal Authority": "Immortal",
    "Holy Avenger | Paladin's Blade": "Immortal", "Vorpal Sword | Snicker-Snack": "Legendary",
    "Dagger of Venom | Assassin's Tool": "Mythical", "Mace of Disruption | Undead Bane": "Legendary",
    "Sun Blade | Sword of Light": "Legendary", "Frostmourne | Lich King's Blade": "Immortal",
    "Warglaives of Azzinoth | Twin Blades": "Immortal", "Thunderfury | Blessed Blade": "Immortal",
    "Sulfuras | Hand of Ragnaros": "Immortal", "Atiesh | Greatstaff of the Guardian": "Immortal",
    "Shadowmourne | Legendary Axe": "Immortal", "Dragonfang Blade | Ancient Dagger": "Legendary",
    "Ashbringer | Purified Blade": "Immortal", "The Master Sword | Blade of Evil's Bane": "Immortal",
    "Energy Sword | Sangheili Blade": "Legendary", "Gravity Hammer | Brute's Power": "Legendary",
    "Scorpion Flail | Chain Whip": "Rare", "Meteor Hammer | Rope Dart": "Mythical",
    "Urumi | Whip Sword": "Legendary",
    "Kris | Wavy Blade": "Rare", " Katar | Punching Dagger": "Uncommon",
    "Macuahuitl | Obsidian Sword": "Mythical",
    "Tepoztopilli | Aztec Spear": "Rare", "Atlatl | Spear-Thrower": "Uncommon",
    "Slingstaff | Staff Sling": "Uncommon",
    "Chakram | Ring Blade": "Mythical", "Wind and Fire Wheels | Twin Hoops": "Legendary",
    "Three-Section Staff | Coiling Dragon": "Legendary", "Hook Swords | Tiger Hook": "Mythical",
    "Butterfly Swords | Wing Chun Blades": "Rare", "Emeici | Piercing Daggers": "Rare",
    "Monk's Spade | Crescent Shovel": "Mythical", "Nine-Dragon Trident | Imperial Guard": "Legendary",
    "Beam Katana | Energy Blade": "Legendary", "Vibroblade | High-Frequency Blade": "Mythical",
    "Power Fist | Hydraulic Gauntlet": "Legendary", "Chainsword | Ripping Teeth": "Legendary",
    "Thunder Hammer | Percussive Force": "Immortal", "Force Halberd | Energy Polearm": "Immortal",
    "Crozius Arcanum | Staff of Office": "Legendary", "Power Axe | Energy Cleaver": "Mythical",
    "Lightning Claw | Voltaic Talons": "Legendary", "Buster Sword | Cloud's Blade": "Immortal",
    "Gunblade | Revolver Sword": "Legendary", "Keyblade | Key to All Hearts": "Immortal",
    "Rebellion | Dante's Sword": "Legendary", "Alastor | Spirit Sword": "Mythical",
    "Sparda Sword | Demon Power": "Immortal", "Yamato | Vergil's Katana": "Immortal",
    "Masamune | Sephiroth's Blade": "Immortal", "Brotherhood | Tidus's Water Sword": "Legendary",
    "Soul Edge | Demonic Sword": "Immortal", "Soul Calibur | Holy Sword": "Immortal",
    "Blades of Chaos | Kratos's Blades": "Immortal", "Leviathan Axe | Kratos's Axe": "Immortal",
    "Hidden Blade | Assassin's Gauntlet": "Mythical", "Phantom Blade | Crossbow Gauntlet": "Legendary",
    "Saw Cleaver | Hunter's Weapon": "Rare", "Threaded Cane | Whip-Cane": "Mythical",
    "Kirkhammer | Hammer-Sword": "Legendary", "Ludwig's Holy Blade | Transforming Greatsword": "Legendary",
    "Rakuyo | Twinblade": "Legendary", "Moonlight Greatsword | Abyssal Blade": "Immortal",
    "Dragonslayer | Guts's Greatsword": "Immortal", "Falchion | Undead Slayer": "Rare",
    "Uchigatana | Samurai's Blade": "Uncommon", "Zweihander | Ultra Greatsword": "Mythical",
    "Great Scythe | Reaper's Tool": "Rare", "Dark Sword | Abyss Walker": "Legendary",
    "Black Knight Greataxe | Chaos Weapon": "Legendary", "Smough's Hammer | Executioner's Hammer": "Immortal"
}